{
  "page": 18,
  "width": 960.0,
  "height": 540.0,
  "texts": [
    {
      "text": "17",
      "x": 899.2,
      "y": 505.2,
      "w": 10.3,
      "h": 11.2,
      "font": "HendersonBCGSans-Light",
      "size": 10.0,
      "color": "#7f7f7f",
      "flags": 0
    },
    {
      "text": "Copyright © 2026 by Boston Consulting Group. All rights reserved.",
      "x": 945.1,
      "y": 317.0,
      "w": 7.8,
      "h": 197.9,
      "font": "HendersonBCGSans-Light",
      "size": 7.0,
      "color": "#7f7f7f",
      "flags": 0
    },
    {
      "text": "Data | ",
      "x": 49.6,
      "y": 31.9,
      "w": 73.3,
      "h": 26.9,
      "font": "HendersonBCGSans-Bold",
      "size": 24.0,
      "color": "#41ff94",
      "flags": 16
    },
    {
      "text": "Without agent-ready data, nothing scales",
      "x": 123.1,
      "y": 31.9,
      "w": 466.7,
      "h": 26.9,
      "font": "HendersonBCGSans-Bold",
      "size": 24.0,
      "color": "#ffffff",
      "flags": 16
    },
    {
      "text": "1",
      "x": 82.2,
      "y": 257.1,
      "w": 7.3,
      "h": 15.7,
      "font": "HendersonBCGSans-Light",
      "size": 14.0,
      "color": "#000000",
      "flags": 0
    },
    {
      "text": "2",
      "x": 170.6,
      "y": 266.4,
      "w": 7.3,
      "h": 15.7,
      "font": "HendersonBCGSans-Light",
      "size": 14.0,
      "color": "#000000",
      "flags": 0
    },
    {
      "text": "3",
      "x": 119.9,
      "y": 335.8,
      "w": 7.3,
      "h": 15.7,
      "font": "HendersonBCGSans-Light",
      "size": 14.0,
      "color": "#000000",
      "flags": 0
    },
    {
      "text": "Business context fabric",
      "x": 271.1,
      "y": 121.3,
      "w": 155.3,
      "h": 15.7,
      "font": "HendersonBCGSans-Bold",
      "size": 14.0,
      "color": "#00612a",
      "flags": 16
    },
    {
      "text": "•",
      "x": 257.4,
      "y": 144.4,
      "w": 6.3,
      "h": 13.7,
      "font": "TrebuchetMS",
      "size": 12.0,
      "color": "#00c255",
      "flags": 0
    },
    {
      "text": "Agents need more than data; they need ",
      "x": 271.2,
      "y": 144.7,
      "w": 194.7,
      "h": 13.4,
      "font": "HendersonBCGSans-Light",
      "size": 12.0,
      "color": "#000000",
      "flags": 0
    },
    {
      "text": "business context",
      "x": 466.0,
      "y": 144.7,
      "w": 91.2,
      "h": 13.4,
      "font": "HendersonBCGSans-Bold",
      "size": 12.0,
      "color": "#000000",
      "flags": 16
    },
    {
      "text": ", including:",
      "x": 556.8,
      "y": 144.7,
      "w": 52.3,
      "h": 13.4,
      "font": "HendersonBCGSans-Light",
      "size": 12.0,
      "color": "#000000",
      "flags": 0
    },
    {
      "text": "–",
      "x": 284.1,
      "y": 158.8,
      "w": 4.4,
      "h": 13.7,
      "font": "TrebuchetMS",
      "size": 12.0,
      "color": "#00c255",
      "flags": 0
    },
    {
      "text": "Objectives",
      "x": 301.2,
      "y": 159.1,
      "w": 56.4,
      "h": 13.4,
      "font": "HendersonBCGSans-Bold",
      "size": 12.0,
      "color": "#000000",
      "flags": 16
    },
    {
      "text": " – outcomes, not outputs",
      "x": 357.2,
      "y": 159.1,
      "w": 121.1,
      "h": 13.4,
      "font": "HendersonBCGSans-Light",
      "size": 12.0,
      "color": "#000000",
      "flags": 0
    },
    {
      "text": "–",
      "x": 284.1,
      "y": 173.2,
      "w": 4.4,
      "h": 13.7,
      "font": "TrebuchetMS",
      "size": 12.0,
      "color": "#00c255",
      "flags": 0
    },
    {
      "text": "Resources",
      "x": 301.2,
      "y": 173.5,
      "w": 56.3,
      "h": 13.4,
      "font": "HendersonBCGSans-Bold",
      "size": 12.0,
      "color": "#000000",
      "flags": 16
    },
    {
      "text": " – tools and data",
      "x": 357.1,
      "y": 173.5,
      "w": 81.7,
      "h": 13.4,
      "font": "HendersonBCGSans-Light",
      "size": 12.0,
      "color": "#000000",
      "flags": 0
    },
    {
      "text": "–",
      "x": 284.1,
      "y": 187.5,
      "w": 4.4,
      "h": 13.8,
      "font": "TrebuchetMS",
      "size": 12.0,
      "color": "#00c255",
      "flags": 0
    },
    {
      "text": "Constraints",
      "x": 301.2,
      "y": 187.9,
      "w": 62.4,
      "h": 13.5,
      "font": "HendersonBCGSans-Bold",
      "size": 12.0,
      "color": "#000000",
      "flags": 16
    },
    {
      "text": " – brand tone and regulatory limits",
      "x": 363.2,
      "y": 187.9,
      "w": 168.3,
      "h": 13.5,
      "font": "HendersonBCGSans-Light",
      "size": 12.0,
      "color": "#000000",
      "flags": 0
    },
    {
      "text": "1",
      "x": 654.7,
      "y": 157.0,
      "w": 5.2,
      "h": 11.2,
      "font": "HendersonBCGSans-Light",
      "size": 10.0,
      "color": "#ffffff",
      "flags": 0
    },
    {
      "text": "Well-connected integration",
      "x": 672.0,
      "y": 153.6,
      "w": 154.9,
      "h": 13.4,
      "font": "HendersonBCGSans-Bold",
      "size": 12.0,
      "color": "#000000",
      "flags": 16
    },
    {
      "text": "across ",
      "x": 830.0,
      "y": 153.6,
      "w": 35.5,
      "h": 13.4,
      "font": "HendersonBCGSans-Light",
      "size": 12.0,
      "color": "#000000",
      "flags": 0
    },
    {
      "text": "network logs, customer interaction history, ",
      "x": 672.0,
      "y": 168.0,
      "w": 220.1,
      "h": 13.4,
      "font": "HendersonBCGSans-Light",
      "size": 12.0,
      "color": "#000000",
      "flags": 0
    },
    {
      "text": "and tariff structures",
      "x": 672.0,
      "y": 182.4,
      "w": 101.9,
      "h": 13.4,
      "font": "HendersonBCGSans-Light",
      "size": 12.0,
      "color": "#000000",
      "flags": 0
    },
    {
      "text": "2",
      "x": 654.7,
      "y": 226.7,
      "w": 5.2,
      "h": 11.2,
      "font": "HendersonBCGSans-Light",
      "size": 10.0,
      "color": "#ffffff",
      "flags": 0
    },
    {
      "text": "Must mine thousands of data records",
      "x": 672.0,
      "y": 222.7,
      "w": 213.3,
      "h": 13.4,
      "font": "HendersonBCGSans-Bold",
      "size": 12.0,
      "color": "#000000",
      "flags": 16
    },
    {
      "text": "daily ",
      "x": 672.0,
      "y": 237.1,
      "w": 30.7,
      "h": 13.4,
      "font": "HendersonBCGSans-Bold",
      "size": 12.0,
      "color": "#000000",
      "flags": 16
    },
    {
      "text": "to surface relevant insights ",
      "x": 702.8,
      "y": 237.1,
      "w": 141.0,
      "h": 13.4,
      "font": "HendersonBCGSans-Light",
      "size": 12.0,
      "color": "#000000",
      "flags": 0
    },
    {
      "text": "3",
      "x": 654.7,
      "y": 280.9,
      "w": 5.2,
      "h": 11.2,
      "font": "HendersonBCGSans-Light",
      "size": 10.0,
      "color": "#ffffff",
      "flags": 0
    },
    {
      "text": "Users must be equipped with intuitive ",
      "x": 672.0,
      "y": 277.2,
      "w": 221.1,
      "h": 13.4,
      "font": "HendersonBCGSans-Bold",
      "size": 12.0,
      "color": "#000000",
      "flags": 16
    },
    {
      "text": "platforms ",
      "x": 672.0,
      "y": 291.6,
      "w": 58.8,
      "h": 13.4,
      "font": "HendersonBCGSans-Bold",
      "size": 12.0,
      "color": "#000000",
      "flags": 16
    },
    {
      "text": "to interact with and supervise ",
      "x": 731.0,
      "y": 291.6,
      "w": 154.9,
      "h": 13.4,
      "font": "HendersonBCGSans-Light",
      "size": 12.0,
      "color": "#000000",
      "flags": 0
    },
    {
      "text": "agents",
      "x": 672.0,
      "y": 306.0,
      "w": 34.1,
      "h": 13.4,
      "font": "HendersonBCGSans-Light",
      "size": 12.0,
      "color": "#000000",
      "flags": 0
    },
    {
      "text": "4",
      "x": 654.7,
      "y": 349.5,
      "w": 5.2,
      "h": 11.2,
      "font": "HendersonBCGSans-Light",
      "size": 10.0,
      "color": "#ffffff",
      "flags": 0
    },
    {
      "text": "Continuous monitoring ",
      "x": 672.0,
      "y": 346.2,
      "w": 135.3,
      "h": 13.4,
      "font": "HendersonBCGSans-Bold",
      "size": 12.0,
      "color": "#000000",
      "flags": 16
    },
    {
      "text": "and ",
      "x": 807.2,
      "y": 346.2,
      "w": 22.7,
      "h": 13.4,
      "font": "HendersonBCGSans-Light",
      "size": 12.0,
      "color": "#000000",
      "flags": 0
    },
    {
      "text": "enhancements",
      "x": 672.0,
      "y": 360.6,
      "w": 85.0,
      "h": 13.4,
      "font": "HendersonBCGSans-Bold",
      "size": 12.0,
      "color": "#000000",
      "flags": 16
    },
    {
      "text": "are essential to ensure the ",
      "x": 760.2,
      "y": 360.6,
      "w": 139.7,
      "h": 13.4,
      "font": "HendersonBCGSans-Light",
      "size": 12.0,
      "color": "#000000",
      "flags": 0
    },
    {
      "text": "capability scales and adapts with the business",
      "x": 672.0,
      "y": 375.0,
      "w": 236.3,
      "h": 13.5,
      "font": "HendersonBCGSans-Light",
      "size": 12.0,
      "color": "#000000",
      "flags": 0
    },
    {
      "text": "Bringing this to life across telcos",
      "x": 650.7,
      "y": 121.3,
      "w": 206.5,
      "h": 15.7,
      "font": "HendersonBCGSans-Bold",
      "size": 14.0,
      "color": "#00612a",
      "flags": 16
    },
    {
      "text": "Data products for agents",
      "x": 271.1,
      "y": 362.4,
      "w": 164.1,
      "h": 15.7,
      "font": "HendersonBCGSans-Bold",
      "size": 14.0,
      "color": "#00913f",
      "flags": 16
    },
    {
      "text": "•",
      "x": 257.4,
      "y": 381.7,
      "w": 6.3,
      "h": 13.7,
      "font": "TrebuchetMS",
      "size": 12.0,
      "color": "#00c255",
      "flags": 0
    },
    {
      "text": "Data teams must shift towards ",
      "x": 271.2,
      "y": 382.1,
      "w": 152.3,
      "h": 13.4,
      "font": "HendersonBCGSans-Light",
      "size": 12.0,
      "color": "#000000",
      "flags": 0
    },
    {
      "text": "exposing data via APIs and model ",
      "x": 423.7,
      "y": 382.1,
      "w": 186.6,
      "h": 13.4,
      "font": "HendersonBCGSans-Bold",
      "size": 12.0,
      "color": "#000000",
      "flags": 16
    },
    {
      "text": "context protocol",
      "x": 271.2,
      "y": 396.5,
      "w": 87.4,
      "h": 13.4,
      "font": "HendersonBCGSans-Bold",
      "size": 12.0,
      "color": "#000000",
      "flags": 16
    },
    {
      "text": "(MCP) that agents can call autonomously",
      "x": 362.4,
      "y": 396.5,
      "w": 201.1,
      "h": 13.4,
      "font": "HendersonBCGSans-Light",
      "size": 12.0,
      "color": "#000000",
      "flags": 0
    },
    {
      "text": "•",
      "x": 257.4,
      "y": 410.5,
      "w": 6.3,
      "h": 13.7,
      "font": "TrebuchetMS",
      "size": 12.0,
      "color": "#00c255",
      "flags": 0
    },
    {
      "text": "Federated data ownership",
      "x": 271.2,
      "y": 410.9,
      "w": 142.5,
      "h": 13.4,
      "font": "HendersonBCGSans-Bold",
      "size": 12.0,
      "color": "#000000",
      "flags": 16
    },
    {
      "text": ", with business teams owning data while ",
      "x": 413.3,
      "y": 410.9,
      "w": 198.0,
      "h": 13.4,
      "font": "HendersonBCGSans-Light",
      "size": 12.0,
      "color": "#000000",
      "flags": 0
    },
    {
      "text": "platforms expose it via APIs for agent consumption",
      "x": 271.2,
      "y": 425.3,
      "w": 246.3,
      "h": 13.4,
      "font": "HendersonBCGSans-Light",
      "size": 12.0,
      "color": "#000000",
      "flags": 0
    },
    {
      "text": "•",
      "x": 257.4,
      "y": 439.3,
      "w": 6.3,
      "h": 13.7,
      "font": "TrebuchetMS",
      "size": 12.0,
      "color": "#00c255",
      "flags": 0
    },
    {
      "text": "Data-driven decision-making culture",
      "x": 271.2,
      "y": 439.7,
      "w": 196.5,
      "h": 13.4,
      "font": "HendersonBCGSans-Bold",
      "size": 12.0,
      "color": "#000000",
      "flags": 16
    },
    {
      "text": ", with shared playbooks and ",
      "x": 467.4,
      "y": 439.7,
      "w": 137.4,
      "h": 13.4,
      "font": "HendersonBCGSans-Light",
      "size": 12.0,
      "color": "#000000",
      "flags": 0
    },
    {
      "text": "templates to standardize high-quality agent-supported decisions",
      "x": 271.2,
      "y": 454.1,
      "w": 309.9,
      "h": 13.4,
      "font": "HendersonBCGSans-Light",
      "size": 12.0,
      "color": "#000000",
      "flags": 0
    },
    {
      "text": "3",
      "x": 254.6,
      "y": 362.9,
      "w": 6.9,
      "h": 14.9,
      "font": "HendersonBCGSans-Light",
      "size": 13.3,
      "color": "#ffffff",
      "flags": 0
    },
    {
      "text": "Unstructured data ready for agent retrieval",
      "x": 271.1,
      "y": 238.5,
      "w": 287.0,
      "h": 15.7,
      "font": "HendersonBCGSans-Bold",
      "size": 14.0,
      "color": "#00c255",
      "flags": 16
    },
    {
      "text": "•",
      "x": 257.4,
      "y": 261.8,
      "w": 6.3,
      "h": 13.7,
      "font": "TrebuchetMS",
      "size": 12.0,
      "color": "#00c255",
      "flags": 0
    },
    {
      "text": "Enable retrieval over unstructured data ",
      "x": 271.2,
      "y": 262.2,
      "w": 216.2,
      "h": 13.4,
      "font": "HendersonBCGSans-Bold",
      "size": 12.0,
      "color": "#000000",
      "flags": 16
    },
    {
      "text": "by converting documents ",
      "x": 487.4,
      "y": 262.2,
      "w": 125.0,
      "h": 13.4,
      "font": "HendersonBCGSans-Light",
      "size": 12.0,
      "color": "#000000",
      "flags": 0
    },
    {
      "text": "(e.g., contracts and network manuals) into searchable formats that ",
      "x": 271.2,
      "y": 276.6,
      "w": 326.0,
      "h": 13.4,
      "font": "HendersonBCGSans-Light",
      "size": 12.0,
      "color": "#000000",
      "flags": 0
    },
    {
      "text": "agents can retrieve at runtime",
      "x": 271.2,
      "y": 291.0,
      "w": 146.7,
      "h": 13.4,
      "font": "HendersonBCGSans-Light",
      "size": 12.0,
      "color": "#000000",
      "flags": 0
    },
    {
      "text": "•",
      "x": 257.4,
      "y": 305.0,
      "w": 6.3,
      "h": 13.7,
      "font": "TrebuchetMS",
      "size": 12.0,
      "color": "#00c255",
      "flags": 0
    },
    {
      "text": "Implement short- and long-term agent memory ",
      "x": 271.2,
      "y": 305.4,
      "w": 258.7,
      "h": 13.4,
      "font": "HendersonBCGSans-Bold",
      "size": 12.0,
      "color": "#000000",
      "flags": 16
    },
    {
      "text": "(session and ",
      "x": 530.3,
      "y": 305.4,
      "w": 63.7,
      "h": 13.4,
      "font": "HendersonBCGSans-Light",
      "size": 12.0,
      "color": "#000000",
      "flags": 0
    },
    {
      "text": "episodic or semantic) to retain and reuse interaction history",
      "x": 271.2,
      "y": 319.8,
      "w": 288.8,
      "h": 13.5,
      "font": "HendersonBCGSans-Light",
      "size": 12.0,
      "color": "#000000",
      "flags": 0
    },
    {
      "text": "2",
      "x": 254.6,
      "y": 239.0,
      "w": 6.9,
      "h": 14.9,
      "font": "HendersonBCGSans-Light",
      "size": 13.3,
      "color": "#ffffff",
      "flags": 0
    },
    {
      "text": "1",
      "x": 254.6,
      "y": 121.8,
      "w": 6.9,
      "h": 14.9,
      "font": "HendersonBCGSans-Light",
      "size": 13.3,
      "color": "#ffffff",
      "flags": 0
    },
    {
      "text": "Data teams",
      "x": 91.4,
      "y": 368.0,
      "w": 70.0,
      "h": 15.7,
      "font": "HendersonBCGSans-Light",
      "size": 14.0,
      "color": "#00913f",
      "flags": 0
    },
    {
      "text": "Data ",
      "x": 169.8,
      "y": 201.5,
      "w": 32.8,
      "h": 15.7,
      "font": "HendersonBCGSans-Light",
      "size": 14.0,
      "color": "#00c255",
      "flags": 0
    },
    {
      "text": "stack",
      "x": 168.7,
      "y": 218.3,
      "w": 31.4,
      "h": 15.7,
      "font": "HendersonBCGSans-Light",
      "size": 14.0,
      "color": "#00c255",
      "flags": 0
    },
    {
      "text": "Data ",
      "x": 51.5,
      "y": 201.5,
      "w": 32.8,
      "h": 15.7,
      "font": "HendersonBCGSans-Light",
      "size": 14.0,
      "color": "#00612a",
      "flags": 0
    },
    {
      "text": "model",
      "x": 47.0,
      "y": 218.3,
      "w": 38.1,
      "h": 15.7,
      "font": "HendersonBCGSans-Light",
      "size": 14.0,
      "color": "#00612a",
      "flags": 0
    },
    {
      "text": "Source: BCG analysis. ",
      "x": 49.6,
      "y": 505.3,
      "w": 96.3,
      "h": 11.2,
      "font": "HendersonBCGSans-Light",
      "size": 10.0,
      "color": "#000000",
      "flags": 0
    },
    {
      "text": "Key takeaway: ",
      "x": 662.7,
      "y": 416.5,
      "w": 83.7,
      "h": 13.4,
      "font": "HendersonBCGSans-Bold",
      "size": 12.0,
      "color": "#00612a",
      "flags": 16
    },
    {
      "text": "Data must be treated as a ",
      "x": 746.5,
      "y": 416.5,
      "w": 151.0,
      "h": 13.4,
      "font": "HendersonBCGSans-Bold",
      "size": 12.0,
      "color": "#000000",
      "flags": 16
    },
    {
      "text": "critical enterprise asset; investing in ",
      "x": 662.7,
      "y": 430.9,
      "w": 210.3,
      "h": 13.5,
      "font": "HendersonBCGSans-Bold",
      "size": 12.0,
      "color": "#000000",
      "flags": 16
    },
    {
      "text": "quality, governance, and management is ",
      "x": 662.7,
      "y": 445.3,
      "w": 232.9,
      "h": 13.5,
      "font": "HendersonBCGSans-Bold",
      "size": 12.0,
      "color": "#000000",
      "flags": 16
    },
    {
      "text": "essential for scaling agents across telcos",
      "x": 662.7,
      "y": 459.7,
      "w": 231.8,
      "h": 13.4,
      "font": "HendersonBCGSans-Bold",
      "size": 12.0,
      "color": "#000000",
      "flags": 16
    }
  ],
  "drawings": [
    {
      "type": "f",
      "x": 0.0,
      "y": -0.0,
      "w": 960.0,
      "h": 540.0,
      "fill": "(1.0, 1.0, 1.0)",
      "color": null,
      "stroke_opacity": null,
      "fill_opacity": 1.0
    },
    {
      "type": "f",
      "x": 0.0,
      "y": 0.0,
      "w": 960.0,
      "h": 92.3,
      "fill": "(0.015699999406933784, 0.019600000232458115, 0.019600000232458115)",
      "color": null,
      "stroke_opacity": null,
      "fill_opacity": 1.0
    },
    {
      "type": "s",
      "x": 0.0,
      "y": 92.3,
      "w": 960.0,
      "h": 0.0,
      "fill": null,
      "color": "(0.0, 0.7609999775886536, 0.3330000042915344)",
      "stroke_opacity": 1.0,
      "fill_opacity": null
    },
    {
      "type": "f",
      "x": -0.7,
      "y": -43.5,
      "w": 28.4,
      "h": 28.4,
      "fill": "(0.0, 0.3799999952316284, 0.16500000655651093)",
      "color": null,
      "stroke_opacity": null,
      "fill_opacity": 1.0
    },
    {
      "type": "f",
      "x": 37.0,
      "y": -43.5,
      "w": 28.4,
      "h": 28.4,
      "fill": "(0.0, 0.5690000057220459, 0.24699999392032623)",
      "color": null,
      "stroke_opacity": null,
      "fill_opacity": 1.0
    },
    {
      "type": "f",
      "x": 74.7,
      "y": -43.5,
      "w": 28.4,
      "h": 28.4,
      "fill": "(0.2549999952316284, 1.0, 0.5799999833106995)",
      "color": null,
      "stroke_opacity": null,
      "fill_opacity": 1.0
    },
    {
      "type": "f",
      "x": 112.4,
      "y": -43.5,
      "w": 28.4,
      "h": 28.4,
      "fill": "(0.0, 0.7609999775886536, 0.3330000042915344)",
      "color": null,
      "stroke_opacity": null,
      "fill_opacity": 1.0
    },
    {
      "type": "f",
      "x": 150.2,
      "y": -43.5,
      "w": 28.4,
      "h": 28.4,
      "fill": "(0.0, 0.0, 0.0)",
      "color": null,
      "stroke_opacity": null,
      "fill_opacity": 1.0
    },
    {
      "type": "f",
      "x": 187.9,
      "y": -43.5,
      "w": 28.4,
      "h": 28.4,
      "fill": "(0.2199999988079071, 0.2240000069141388, 0.2199999988079071)",
      "color": null,
      "stroke_opacity": null,
      "fill_opacity": 1.0
    },
    {
      "type": "f",
      "x": 21.8,
      "y": 117.6,
      "w": 210.7,
      "h": 367.4,
      "fill": "(0.8510000109672546, 1.0, 0.9179999828338623)",
      "color": null,
      "stroke_opacity": null,
      "fill_opacity": 1.0
    },
    {
      "type": "f",
      "x": 55.2,
      "y": 222.6,
      "w": 73.7,
      "h": 101.1,
      "fill": "(0.0, 0.3799999952316284, 0.16500000655651093)",
      "color": null,
      "stroke_opacity": null,
      "fill_opacity": 1.0
    },
    {
      "type": "f",
      "x": 67.6,
      "y": 311.1,
      "w": 117.6,
      "h": 53.0,
      "fill": "(0.0, 0.5690000057220459, 0.24699999392032623)",
      "color": null,
      "stroke_opacity": null,
      "fill_opacity": 1.0
    },
    {
      "type": "f",
      "x": 130.7,
      "y": 222.9,
      "w": 65.3,
      "h": 102.8,
      "fill": "(0.0, 0.7609999775886536, 0.3330000042915344)",
      "color": null,
      "stroke_opacity": null,
      "fill_opacity": 1.0
    },
    {
      "type": "f",
      "x": 76.3,
      "y": 254.9,
      "w": 19.3,
      "h": 19.3,
      "fill": "(1.0, 1.0, 1.0)",
      "color": null,
      "stroke_opacity": null,
      "fill_opacity": 1.0
    },
    {
      "type": "f",
      "x": 164.6,
      "y": 264.3,
      "w": 19.3,
      "h": 19.3,
      "fill": "(1.0, 1.0, 1.0)",
      "color": null,
      "stroke_opacity": null,
      "fill_opacity": 1.0
    },
    {
      "type": "f",
      "x": 113.9,
      "y": 333.6,
      "w": 19.3,
      "h": 19.3,
      "fill": "(1.0, 1.0, 1.0)",
      "color": null,
      "stroke_opacity": null,
      "fill_opacity": 1.0
    },
    {
      "type": "f",
      "x": 245.9,
      "y": 117.6,
      "w": 377.2,
      "h": 101.2,
      "fill": "(0.9489127993583679, 0.9490348696708679, 0.9488822817802429)",
      "color": null,
      "stroke_opacity": null,
      "fill_opacity": 1.0
    },
    {
      "type": "f",
      "x": 647.9,
      "y": 152.8,
      "w": 18.8,
      "h": 18.8,
      "fill": "(0.6039368510246277, 0.6040284037590027, 0.6039215922355652)",
      "color": null,
      "stroke_opacity": null,
      "fill_opacity": 1.0
    },
    {
      "type": "f",
      "x": 647.9,
      "y": 222.5,
      "w": 18.8,
      "h": 18.8,
      "fill": "(0.6039368510246277, 0.6040284037590027, 0.6039215922355652)",
      "color": null,
      "stroke_opacity": null,
      "fill_opacity": 1.0
    },
    {
      "type": "f",
      "x": 647.9,
      "y": 276.8,
      "w": 18.8,
      "h": 18.8,
      "fill": "(0.6039368510246277, 0.6040284037590027, 0.6039215922355652)",
      "color": null,
      "stroke_opacity": null,
      "fill_opacity": 1.0
    },
    {
      "type": "f",
      "x": 647.9,
      "y": 345.4,
      "w": 18.8,
      "h": 18.8,
      "fill": "(0.6039368510246277, 0.6040284037590027, 0.6039215922355652)",
      "color": null,
      "stroke_opacity": null,
      "fill_opacity": 1.0
    },
    {
      "type": "f",
      "x": 245.9,
      "y": 358.4,
      "w": 377.2,
      "h": 126.5,
      "fill": "(0.9489127993583679, 0.9490348696708679, 0.9488822817802429)",
      "color": null,
      "stroke_opacity": null,
      "fill_opacity": 1.0
    },
    {
      "type": "f",
      "x": 249.5,
      "y": 361.4,
      "w": 17.1,
      "h": 17.1,
      "fill": "(0.0, 0.5690000057220459, 0.24699999392032623)",
      "color": null,
      "stroke_opacity": null,
      "fill_opacity": 1.0
    },
    {
      "type": "f",
      "x": 245.9,
      "y": 234.7,
      "w": 377.2,
      "h": 107.9,
      "fill": "(0.9489127993583679, 0.9490348696708679, 0.9488822817802429)",
      "color": null,
      "stroke_opacity": null,
      "fill_opacity": 1.0
    },
    {
      "type": "f",
      "x": 249.5,
      "y": 237.5,
      "w": 17.1,
      "h": 17.1,
      "fill": "(0.0, 0.7609999775886536, 0.3330000042915344)",
      "color": null,
      "stroke_opacity": null,
      "fill_opacity": 1.0
    },
    {
      "type": "f",
      "x": 249.5,
      "y": 120.3,
      "w": 17.1,
      "h": 17.1,
      "fill": "(0.0, 0.3799999952316284, 0.16500000655651093)",
      "color": null,
      "stroke_opacity": null,
      "fill_opacity": 1.0
    },
    {
      "type": "s",
      "x": 649.5,
      "y": 209.2,
      "w": 264.7,
      "h": 0.0,
      "fill": null,
      "color": "(0.2549999952316284, 1.0, 0.5799999833106995)",
      "stroke_opacity": 1.0,
      "fill_opacity": null
    },
    {
      "type": "s",
      "x": 649.5,
      "y": 263.6,
      "w": 264.7,
      "h": 0.0,
      "fill": null,
      "color": "(0.2549999952316284, 1.0, 0.5799999833106995)",
      "stroke_opacity": 1.0,
      "fill_opacity": null
    },
    {
      "type": "s",
      "x": 649.5,
      "y": 332.7,
      "w": 264.7,
      "h": 0.0,
      "fill": null,
      "color": "(0.2549999952316284, 1.0, 0.5799999833106995)",
      "stroke_opacity": 1.0,
      "fill_opacity": null
    },
    {
      "type": "s",
      "x": 655.4,
      "y": 404.0,
      "w": 264.6,
      "h": 80.9,
      "fill": null,
      "color": "(0.0, 0.3799999952316284, 0.16500000655651093)",
      "stroke_opacity": 1.0,
      "fill_opacity": null
    },
    {
      "type": "fs",
      "x": 642.1,
      "y": 395.6,
      "w": 21.9,
      "h": 21.9,
      "fill": "(0.0, 0.3799999952316284, 0.16500000655651093)",
      "color": "(1.0, 1.0, 1.0)",
      "stroke_opacity": 1.0,
      "fill_opacity": 1.0
    },
    {
      "type": "fs",
      "x": 651.8,
      "y": 400.6,
      "w": 2.5,
      "h": 12.0,
      "fill": "(1.0, 1.0, 1.0)",
      "color": "(1.0, 1.0, 1.0)",
      "stroke_opacity": 1.0,
      "fill_opacity": 1.0
    }
  ],
  "images": [
    {
      "xref": 170,
      "x": 558.8,
      "y": 0.0,
      "w": 401.2,
      "h": 89.2
    }
  ]
}