{
  "page": 13,
  "width": 960.0,
  "height": 540.0,
  "texts": [
    {
      "text": "12",
      "x": 899.2,
      "y": 505.2,
      "w": 10.3,
      "h": 11.2,
      "font": "HendersonBCGSans-Light",
      "size": 10.0,
      "color": "#7f7f7f",
      "flags": 0
    },
    {
      "text": "Copyright © 2025 by Boston Consulting Group. All rights reserved.",
      "x": 945.1,
      "y": 317.0,
      "w": 7.8,
      "h": 197.9,
      "font": "HendersonBCGSans-Light",
      "size": 7.0,
      "color": "#7f7f7f",
      "flags": 0
    },
    {
      "text": "Before",
      "x": 49.6,
      "y": 111.4,
      "w": 57.2,
      "h": 20.2,
      "font": "HendersonBCGSans-Bold",
      "size": 18.0,
      "color": "#00c255",
      "flags": 16
    },
    {
      "text": "From tedious process, with variable quality…",
      "x": 49.6,
      "y": 135.6,
      "w": 268.8,
      "h": 15.7,
      "font": "HendersonBCGSans-Light",
      "size": 14.0,
      "color": "#000000",
      "flags": 0
    },
    {
      "text": "After",
      "x": 363.7,
      "y": 111.4,
      "w": 43.4,
      "h": 20.2,
      "font": "HendersonBCGSans-Bold",
      "size": 18.0,
      "color": "#00c255",
      "flags": 16
    },
    {
      "text": "…more robust & consistently written reviews",
      "x": 363.7,
      "y": 135.6,
      "w": 268.6,
      "h": 15.7,
      "font": "HendersonBCGSans-Light",
      "size": 14.0,
      "color": "#000000",
      "flags": 0
    },
    {
      "text": "EXAMPLE | PERFORMANCE MANAGEMENT CASE STUDY",
      "x": 49.6,
      "y": 9.7,
      "w": 389.0,
      "h": 15.7,
      "font": "Arial-BoldMT",
      "size": 14.0,
      "color": "#41ff94",
      "flags": 16
    },
    {
      "text": "Cut review-writing time by ",
      "x": 727.6,
      "y": 155.8,
      "w": 159.6,
      "h": 15.7,
      "font": "HendersonBCGSans-Light",
      "size": 14.0,
      "color": "#575757",
      "flags": 0
    },
    {
      "text": "~45%, ",
      "x": 887.2,
      "y": 155.8,
      "w": 39.0,
      "h": 15.7,
      "font": "HendersonBCGSans-Bold",
      "size": 14.0,
      "color": "#29ba74",
      "flags": 16
    },
    {
      "text": "saving 1,000+",
      "x": 727.6,
      "y": 171.8,
      "w": 86.2,
      "h": 15.8,
      "font": "HendersonBCGSans-Bold",
      "size": 14.1,
      "color": "#29ba74",
      "flags": 16
    },
    {
      "text": "hours of manager ",
      "x": 817.3,
      "y": 171.8,
      "w": 109.9,
      "h": 15.8,
      "font": "HendersonBCGSans-Light",
      "size": 14.1,
      "color": "#575757",
      "flags": 0
    },
    {
      "text": "time – at no incremental cost",
      "x": 727.6,
      "y": 187.8,
      "w": 177.0,
      "h": 15.7,
      "font": "HendersonBCGSans-Light",
      "size": 14.0,
      "color": "#575757",
      "flags": 0
    },
    {
      "text": "Improved review quality ",
      "x": 727.6,
      "y": 213.8,
      "w": 146.9,
      "h": 15.7,
      "font": "HendersonBCGSans-Light",
      "size": 14.0,
      "color": "#575757",
      "flags": 0
    },
    {
      "text": "by ",
      "x": 874.2,
      "y": 213.8,
      "w": 18.0,
      "h": 15.7,
      "font": "HendersonBCGSans-Regular",
      "size": 14.0,
      "color": "#575757",
      "flags": 0
    },
    {
      "text": "22%",
      "x": 892.2,
      "y": 213.8,
      "w": 25.5,
      "h": 15.7,
      "font": "HendersonBCGSans-Bold",
      "size": 14.0,
      "color": "#29ba74",
      "flags": 16
    },
    {
      "text": "2",
      "x": 917.6,
      "y": 213.9,
      "w": 4.9,
      "h": 10.5,
      "font": "HendersonBCGSans-Regular",
      "size": 9.4,
      "color": "#575757",
      "flags": 1
    },
    {
      "text": ", ",
      "x": 922.5,
      "y": 213.8,
      "w": 6.3,
      "h": 15.7,
      "font": "HendersonBCGSans-Light",
      "size": 14.0,
      "color": "#575757",
      "flags": 0
    },
    {
      "text": "driving stronger development ",
      "x": 727.6,
      "y": 229.8,
      "w": 179.6,
      "h": 15.7,
      "font": "HendersonBCGSans-Light",
      "size": 14.0,
      "color": "#575757",
      "flags": 0
    },
    {
      "text": "outcomes",
      "x": 727.6,
      "y": 245.7,
      "w": 58.8,
      "h": 15.7,
      "font": "HendersonBCGSans-Light",
      "size": 14.0,
      "color": "#575757",
      "flags": 0
    },
    {
      "text": "~90% ",
      "x": 727.6,
      "y": 271.7,
      "w": 36.4,
      "h": 15.7,
      "font": "HendersonBCGSans-Bold",
      "size": 14.0,
      "color": "#00c255",
      "flags": 16
    },
    {
      "text": "managers reported ",
      "x": 763.8,
      "y": 271.7,
      "w": 118.2,
      "h": 15.7,
      "font": "HendersonBCGSans-Light",
      "size": 14.0,
      "color": "#575757",
      "flags": 0
    },
    {
      "text": "materially enhanced review ",
      "x": 727.6,
      "y": 287.6,
      "w": 169.1,
      "h": 15.8,
      "font": "HendersonBCGSans-Light",
      "size": 14.1,
      "color": "#575757",
      "flags": 0
    },
    {
      "text": "experienced",
      "x": 727.6,
      "y": 303.6,
      "w": 72.6,
      "h": 15.7,
      "font": "HendersonBCGSans-Light",
      "size": 14.0,
      "color": "#575757",
      "flags": 0
    },
    {
      "text": "The ",
      "x": 727.6,
      "y": 360.7,
      "w": 23.3,
      "h": 15.7,
      "font": "HendersonBCGSans-LightIt",
      "size": 14.0,
      "color": "#575757",
      "flags": 2
    },
    {
      "text": "tool is really useful ",
      "x": 750.9,
      "y": 360.7,
      "w": 105.4,
      "h": 15.7,
      "font": "HendersonBCGSans-LightIt",
      "size": 14.0,
      "color": "#29ba74",
      "flags": 2
    },
    {
      "text": "— ",
      "x": 855.9,
      "y": 362.6,
      "w": 15.6,
      "h": 13.4,
      "font": "HendersonBCGSans-Light",
      "size": 12.0,
      "color": "#00612a",
      "flags": 0
    },
    {
      "text": "for me, the ",
      "x": 871.6,
      "y": 360.7,
      "w": 61.6,
      "h": 15.7,
      "font": "HendersonBCGSans-LightIt",
      "size": 14.0,
      "color": "#575757",
      "flags": 2
    },
    {
      "text": "benefit is about helping to ",
      "x": 727.6,
      "y": 376.7,
      "w": 144.2,
      "h": 15.7,
      "font": "HendersonBCGSans-LightIt",
      "size": 14.0,
      "color": "#575757",
      "flags": 2
    },
    {
      "text": "get started ",
      "x": 871.8,
      "y": 376.7,
      "w": 60.5,
      "h": 15.7,
      "font": "HendersonBCGSans-LightIt",
      "size": 14.0,
      "color": "#29ba74",
      "flags": 2
    },
    {
      "text": "and doing the synthesis",
      "x": 727.6,
      "y": 392.7,
      "w": 127.0,
      "h": 15.7,
      "font": "HendersonBCGSans-LightIt",
      "size": 14.0,
      "color": "#29ba74",
      "flags": 2
    },
    {
      "text": "This tool ",
      "x": 727.6,
      "y": 418.7,
      "w": 50.6,
      "h": 15.7,
      "font": "HendersonBCGSans-LightIt",
      "size": 14.0,
      "color": "#575757",
      "flags": 2
    },
    {
      "text": "changed my life ",
      "x": 778.0,
      "y": 418.7,
      "w": 88.9,
      "h": 15.7,
      "font": "HendersonBCGSans-LightIt",
      "size": 14.0,
      "color": "#29ba74",
      "flags": 2
    },
    {
      "text": "this year-",
      "x": 866.7,
      "y": 418.7,
      "w": 48.8,
      "h": 15.7,
      "font": "HendersonBCGSans-LightIt",
      "size": 14.0,
      "color": "#575757",
      "flags": 2
    },
    {
      "text": "end review season! While it did still ",
      "x": 727.6,
      "y": 434.7,
      "w": 195.0,
      "h": 15.7,
      "font": "HendersonBCGSans-LightIt",
      "size": 14.0,
      "color": "#575757",
      "flags": 2
    },
    {
      "text": "take time, I was able to get all my ",
      "x": 727.6,
      "y": 450.6,
      "w": 186.4,
      "h": 15.7,
      "font": "HendersonBCGSans-LightIt",
      "size": 14.0,
      "color": "#575757",
      "flags": 2
    },
    {
      "text": "reviews turned in on time before ",
      "x": 727.6,
      "y": 466.6,
      "w": 178.2,
      "h": 15.7,
      "font": "HendersonBCGSans-LightIt",
      "size": 14.0,
      "color": "#29ba74",
      "flags": 2
    },
    {
      "text": "the deadline",
      "x": 727.6,
      "y": 482.6,
      "w": 66.7,
      "h": 15.7,
      "font": "HendersonBCGSans-LightIt",
      "size": 14.0,
      "color": "#29ba74",
      "flags": 2
    },
    {
      "text": "What we saw",
      "x": 727.6,
      "y": 114.0,
      "w": 112.1,
      "h": 20.2,
      "font": "HendersonBCGSans-Bold",
      "size": 18.0,
      "color": "#03522d",
      "flags": 16
    },
    {
      "text": "13",
      "x": 206.9,
      "y": 414.9,
      "w": 37.4,
      "h": 40.3,
      "font": "HendersonBCGSans-Bold",
      "size": 36.0,
      "color": "#7f7f7f",
      "flags": 16
    },
    {
      "text": "Starting score",
      "x": 78.0,
      "y": 428.9,
      "w": 106.3,
      "h": 20.2,
      "font": "HendersonBCGSans-Light",
      "size": 18.0,
      "color": "#000000",
      "flags": 0
    },
    {
      "text": "Increased to…",
      "x": 354.3,
      "y": 428.9,
      "w": 113.9,
      "h": 20.2,
      "font": "HendersonBCGSans-Light",
      "size": 18.0,
      "color": "#000000",
      "flags": 0
    },
    {
      "text": "16",
      "x": 484.1,
      "y": 416.0,
      "w": 37.4,
      "h": 40.3,
      "font": "HendersonBCGSans-Bold",
      "size": 36.0,
      "color": "#29ba74",
      "flags": 16
    },
    {
      "text": "22%",
      "x": 573.0,
      "y": 408.8,
      "w": 39.2,
      "h": 24.2,
      "font": "HendersonBCGSans-Light",
      "size": 21.6,
      "color": "#29ba74",
      "flags": 0
    },
    {
      "text": "Increase in review ",
      "x": 550.8,
      "y": 432.5,
      "w": 86.6,
      "h": 12.1,
      "font": "HendersonBCGSans-Light",
      "size": 10.8,
      "color": "#29ba74",
      "flags": 0
    },
    {
      "text": "quality",
      "x": 576.8,
      "y": 445.5,
      "w": 31.8,
      "h": 12.1,
      "font": "HendersonBCGSans-Light",
      "size": 10.8,
      "color": "#29ba74",
      "flags": 0
    },
    {
      "text": "Today’s accessible technology already driving impact; GenAI tool ",
      "x": 49.6,
      "y": 29.2,
      "w": 743.9,
      "h": 26.9,
      "font": "HendersonBCGSans-Bold",
      "size": 24.0,
      "color": "#ffffff",
      "flags": 16
    },
    {
      "text": "to drive enhanced review writing and better manager experience",
      "x": 49.6,
      "y": 55.2,
      "w": 740.2,
      "h": 26.9,
      "font": "HendersonBCGSans-Bold",
      "size": 24.0,
      "color": "#ffffff",
      "flags": 16
    },
    {
      "text": "0%",
      "x": 116.0,
      "y": 364.1,
      "w": 15.5,
      "h": 13.4,
      "font": "HendersonBCGSans-Bold",
      "size": 12.0,
      "color": "#000000",
      "flags": 16
    },
    {
      "text": "5%",
      "x": 116.0,
      "y": 335.6,
      "w": 15.5,
      "h": 13.4,
      "font": "HendersonBCGSans-Bold",
      "size": 12.0,
      "color": "#000000",
      "flags": 16
    },
    {
      "text": "10%",
      "x": 109.8,
      "y": 306.9,
      "w": 21.7,
      "h": 13.4,
      "font": "HendersonBCGSans-Bold",
      "size": 12.0,
      "color": "#000000",
      "flags": 16
    },
    {
      "text": "15%",
      "x": 109.8,
      "y": 278.4,
      "w": 21.8,
      "h": 13.5,
      "font": "HendersonBCGSans-Bold",
      "size": 12.0,
      "color": "#000000",
      "flags": 16
    },
    {
      "text": "20%",
      "x": 109.8,
      "y": 249.8,
      "w": 21.7,
      "h": 13.4,
      "font": "HendersonBCGSans-Bold",
      "size": 12.0,
      "color": "#000000",
      "flags": 16
    },
    {
      "text": "25%",
      "x": 109.8,
      "y": 221.3,
      "w": 21.7,
      "h": 13.4,
      "font": "HendersonBCGSans-Bold",
      "size": 12.0,
      "color": "#000000",
      "flags": 16
    },
    {
      "text": "1",
      "x": 149.6,
      "y": 375.7,
      "w": 6.2,
      "h": 13.4,
      "font": "HendersonBCGSans-Light",
      "size": 12.0,
      "color": "#000000",
      "flags": 0
    },
    {
      "text": "2",
      "x": 176.4,
      "y": 375.7,
      "w": 6.2,
      "h": 13.4,
      "font": "HendersonBCGSans-Light",
      "size": 12.0,
      "color": "#000000",
      "flags": 0
    },
    {
      "text": "3",
      "x": 203.1,
      "y": 375.7,
      "w": 6.2,
      "h": 13.4,
      "font": "HendersonBCGSans-Light",
      "size": 12.0,
      "color": "#000000",
      "flags": 0
    },
    {
      "text": "4",
      "x": 229.8,
      "y": 375.7,
      "w": 6.2,
      "h": 13.4,
      "font": "HendersonBCGSans-Light",
      "size": 12.0,
      "color": "#000000",
      "flags": 0
    },
    {
      "text": "5",
      "x": 256.5,
      "y": 375.7,
      "w": 6.2,
      "h": 13.4,
      "font": "HendersonBCGSans-Light",
      "size": 12.0,
      "color": "#000000",
      "flags": 0
    },
    {
      "text": "6",
      "x": 283.3,
      "y": 375.7,
      "w": 6.2,
      "h": 13.4,
      "font": "HendersonBCGSans-Light",
      "size": 12.0,
      "color": "#000000",
      "flags": 0
    },
    {
      "text": "7",
      "x": 310.0,
      "y": 375.7,
      "w": 6.2,
      "h": 13.4,
      "font": "HendersonBCGSans-Light",
      "size": 12.0,
      "color": "#000000",
      "flags": 0
    },
    {
      "text": "8",
      "x": 336.8,
      "y": 375.7,
      "w": 6.2,
      "h": 13.4,
      "font": "HendersonBCGSans-Light",
      "size": 12.0,
      "color": "#000000",
      "flags": 0
    },
    {
      "text": "9",
      "x": 363.4,
      "y": 375.7,
      "w": 6.2,
      "h": 13.4,
      "font": "HendersonBCGSans-Light",
      "size": 12.0,
      "color": "#000000",
      "flags": 0
    },
    {
      "text": "10",
      "x": 387.0,
      "y": 375.7,
      "w": 12.5,
      "h": 13.4,
      "font": "HendersonBCGSans-Light",
      "size": 12.0,
      "color": "#000000",
      "flags": 0
    },
    {
      "text": "11",
      "x": 413.8,
      "y": 375.7,
      "w": 12.5,
      "h": 13.4,
      "font": "HendersonBCGSans-Light",
      "size": 12.0,
      "color": "#000000",
      "flags": 0
    },
    {
      "text": "12",
      "x": 440.5,
      "y": 375.7,
      "w": 12.5,
      "h": 13.4,
      "font": "HendersonBCGSans-Light",
      "size": 12.0,
      "color": "#000000",
      "flags": 0
    },
    {
      "text": "13",
      "x": 467.3,
      "y": 375.7,
      "w": 12.5,
      "h": 13.4,
      "font": "HendersonBCGSans-Light",
      "size": 12.0,
      "color": "#000000",
      "flags": 0
    },
    {
      "text": "14",
      "x": 493.9,
      "y": 375.7,
      "w": 12.5,
      "h": 13.4,
      "font": "HendersonBCGSans-Light",
      "size": 12.0,
      "color": "#000000",
      "flags": 0
    },
    {
      "text": "15",
      "x": 520.7,
      "y": 375.7,
      "w": 12.5,
      "h": 13.4,
      "font": "HendersonBCGSans-Light",
      "size": 12.0,
      "color": "#000000",
      "flags": 0
    },
    {
      "text": "16",
      "x": 547.4,
      "y": 375.7,
      "w": 12.5,
      "h": 13.4,
      "font": "HendersonBCGSans-Light",
      "size": 12.0,
      "color": "#000000",
      "flags": 0
    },
    {
      "text": "17",
      "x": 574.2,
      "y": 375.7,
      "w": 12.5,
      "h": 13.4,
      "font": "HendersonBCGSans-Light",
      "size": 12.0,
      "color": "#000000",
      "flags": 0
    },
    {
      "text": "18",
      "x": 600.9,
      "y": 375.7,
      "w": 12.5,
      "h": 13.4,
      "font": "HendersonBCGSans-Light",
      "size": 12.0,
      "color": "#000000",
      "flags": 0
    },
    {
      "text": "19",
      "x": 627.5,
      "y": 375.7,
      "w": 12.5,
      "h": 13.4,
      "font": "HendersonBCGSans-Light",
      "size": 12.0,
      "color": "#000000",
      "flags": 0
    },
    {
      "text": "20",
      "x": 654.3,
      "y": 375.7,
      "w": 12.5,
      "h": 13.4,
      "font": "HendersonBCGSans-Light",
      "size": 12.0,
      "color": "#000000",
      "flags": 0
    },
    {
      "text": "Without tool",
      "x": 167.3,
      "y": 242.8,
      "w": 65.4,
      "h": 12.4,
      "font": "HendersonBCGSans-Bold",
      "size": 11.0,
      "color": "#000000",
      "flags": 16
    },
    {
      "text": "With custom GPT",
      "x": 167.3,
      "y": 261.3,
      "w": 91.0,
      "h": 12.4,
      "font": "HendersonBCGSans-Bold",
      "size": 11.0,
      "color": "#000000",
      "flags": 16
    },
    {
      "text": "Note:  No difference in average performance rating between “no tool” and “with tool” sample",
      "x": 46.6,
      "y": 472.9,
      "w": 399.7,
      "h": 11.2,
      "font": "HendersonBCGSans-Light",
      "size": 10.0,
      "color": "#7f7f7f",
      "flags": 0
    },
    {
      "text": "Source: Structured qualitative assessment of 68 reviews for “no tool” and “with tool” user groups",
      "x": 46.6,
      "y": 483.7,
      "w": 414.3,
      "h": 11.2,
      "font": "HendersonBCGSans-Light",
      "size": 10.0,
      "color": "#7f7f7f",
      "flags": 0
    },
    {
      "text": "1. Each review is independently assessed by 3 HR experts for quality according to a standard rubric and the final score is calculated as the average of ",
      "x": 46.6,
      "y": 494.5,
      "w": 639.2,
      "h": 11.2,
      "font": "HendersonBCGSans-Light",
      "size": 10.0,
      "color": "#7f7f7f",
      "flags": 0
    },
    {
      "text": "their evaluations; 2. Mean (standard deviation) quality score for “with tool” reviews is 15.6 (2.2) and “no tool” reviews 12.8 (3.2) or a 22% higher quality",
      "x": 46.6,
      "y": 505.3,
      "w": 645.5,
      "h": 11.2,
      "font": "HendersonBCGSans-Light",
      "size": 10.0,
      "color": "#7f7f7f",
      "flags": 0
    },
    {
      "text": "Overall quality score distribution: With and without GenAI",
      "x": 198.9,
      "y": 202.0,
      "w": 385.5,
      "h": 15.7,
      "font": "HendersonBCGSans-Bold",
      "size": 14.0,
      "color": "#00c255",
      "flags": 16
    },
    {
      "text": "Quality score (1-20)",
      "x": 337.7,
      "y": 398.5,
      "w": 108.1,
      "h": 13.4,
      "font": "HendersonBCGSans-Bold",
      "size": 12.0,
      "color": "#000000",
      "flags": 16
    },
    {
      "text": "Percentage ",
      "x": 47.7,
      "y": 221.6,
      "w": 62.5,
      "h": 12.4,
      "font": "HendersonBCGSans-Bold",
      "size": 11.0,
      "color": "#000000",
      "flags": 16
    },
    {
      "text": "of users",
      "x": 47.7,
      "y": 234.8,
      "w": 41.5,
      "h": 12.4,
      "font": "HendersonBCGSans-Bold",
      "size": 11.0,
      "color": "#000000",
      "flags": 16
    },
    {
      "text": "Managers spending ~4 hrs * 8 reviewees – ",
      "x": 49.6,
      "y": 157.4,
      "w": 220.3,
      "h": 13.4,
      "font": "HendersonBCGSans-Light",
      "size": 12.0,
      "color": "#00612a",
      "flags": 0
    },
    {
      "text": "with inconsistent quality across reviews",
      "x": 49.6,
      "y": 171.8,
      "w": 202.0,
      "h": 13.4,
      "font": "HendersonBCGSans-Light",
      "size": 12.0,
      "color": "#00612a",
      "flags": 0
    },
    {
      "text": "Faster, better output with custom, proprietary GPT based ",
      "x": 363.7,
      "y": 157.4,
      "w": 293.0,
      "h": 13.4,
      "font": "HendersonBCGSans-Light",
      "size": 12.0,
      "color": "#00612a",
      "flags": 0
    },
    {
      "text": "on Client’s performance mgmt priorities",
      "x": 363.7,
      "y": 171.8,
      "w": 206.4,
      "h": 13.4,
      "font": "HendersonBCGSans-Light",
      "size": 12.0,
      "color": "#00612a",
      "flags": 0
    },
    {
      "text": "1: How CHROs ",
      "x": 859.0,
      "y": 27.0,
      "w": 84.7,
      "h": 13.4,
      "font": "HendersonBCGSans-Bold",
      "size": 12.0,
      "color": "#ffffff",
      "flags": 16
    },
    {
      "text": "will ",
      "x": 859.0,
      "y": 40.0,
      "w": 23.6,
      "h": 13.4,
      "font": "HendersonBCGSans-Bold",
      "size": 12.0,
      "color": "#ffffff",
      "flags": 16
    },
    {
      "text": "deliver HR ",
      "x": 882.7,
      "y": 40.0,
      "w": 63.6,
      "h": 13.4,
      "font": "HendersonBCGSans-Bold",
      "size": 12.0,
      "color": "#41ff94",
      "flags": 16
    },
    {
      "text": "of the future",
      "x": 859.0,
      "y": 53.0,
      "w": 71.7,
      "h": 13.4,
      "font": "HendersonBCGSans-Bold",
      "size": 12.0,
      "color": "#41ff94",
      "flags": 16
    }
  ],
  "drawings": [
    {
      "type": "f",
      "x": 0.0,
      "y": -0.0,
      "w": 960.0,
      "h": 540.0,
      "fill": "(1.0, 1.0, 1.0)",
      "color": null,
      "stroke_opacity": null,
      "fill_opacity": 1.0
    },
    {
      "type": "f",
      "x": 0.0,
      "y": 0.0,
      "w": 960.0,
      "h": 92.3,
      "fill": "(0.015699999406933784, 0.019600000232458115, 0.019600000232458115)",
      "color": null,
      "stroke_opacity": null,
      "fill_opacity": 1.0
    },
    {
      "type": "s",
      "x": 0.0,
      "y": 92.3,
      "w": 960.0,
      "h": 0.0,
      "fill": null,
      "color": "(0.0, 0.7609999775886536, 0.3330000042915344)",
      "stroke_opacity": 1.0,
      "fill_opacity": null
    },
    {
      "type": "s",
      "x": 0.0,
      "y": 92.3,
      "w": 960.0,
      "h": 0.0,
      "fill": null,
      "color": "(0.2549999952316284, 1.0, 0.5799999833106995)",
      "stroke_opacity": 1.0,
      "fill_opacity": null
    },
    {
      "type": "f",
      "x": 693.4,
      "y": 88.3,
      "w": 266.6,
      "h": 451.7,
      "fill": "(0.0940566137433052, 0.0940566137433052, 0.0940566137433052)",
      "color": null,
      "stroke_opacity": null,
      "fill_opacity": 0.05098000168800354
    },
    {
      "type": "fs",
      "x": 255.7,
      "y": 422.7,
      "w": 80.6,
      "h": 26.9,
      "fill": "(0.16099999845027924, 0.36899998784065247, 0.49399998784065247)",
      "color": "(0.16099999845027924, 0.36899998784065247, 0.49399998784065247)",
      "stroke_opacity": 1.0,
      "fill_opacity": 1.0
    },
    {
      "type": "f",
      "x": 580.9,
      "y": 423.6,
      "w": 114.4,
      "h": 56.8,
      "fill": "(1.0, 1.0, 1.0)",
      "color": null,
      "stroke_opacity": null,
      "fill_opacity": 1.0
    },
    {
      "type": "f",
      "x": 526.6,
      "y": 402.8,
      "w": 126.1,
      "h": 68.4,
      "fill": "(0.16099999845027924, 0.36899998784065247, 0.49399998784065247)",
      "color": null,
      "stroke_opacity": null,
      "fill_opacity": 1.0
    },
    {
      "type": "s",
      "x": 133.0,
      "y": 221.4,
      "w": 547.5,
      "h": 155.8,
      "fill": null,
      "color": "(0.0, 0.0, 0.0)",
      "stroke_opacity": 0.0,
      "fill_opacity": null
    },
    {
      "type": "fs",
      "x": 196.1,
      "y": 261.5,
      "w": 464.5,
      "h": 109.1,
      "fill": "(0.7839170098304749, 0.7840390801429749, 0.7839017510414124)",
      "color": "(1.0, 1.0, 1.0)",
      "stroke_opacity": 1.0,
      "fill_opacity": 1.0
    },
    {
      "type": "fs",
      "x": 393.4,
      "y": 253.1,
      "w": 250.8,
      "h": 117.5,
      "fill": "(0.0, 0.7609999775886536, 0.3330000042915344)",
      "color": "(1.0, 1.0, 1.0)",
      "stroke_opacity": 1.0,
      "fill_opacity": 1.0
    },
    {
      "type": "s",
      "x": 139.5,
      "y": 227.9,
      "w": 0.0,
      "h": 142.8,
      "fill": null,
      "color": "(0.6039368510246277, 0.6040284037590027, 0.6039215922355652)",
      "stroke_opacity": 1.0,
      "fill_opacity": null
    },
    {
      "type": "s",
      "x": 139.5,
      "y": 370.6,
      "w": 534.5,
      "h": 0.0,
      "fill": null,
      "color": "(0.6039368510246277, 0.6040284037590027, 0.6039215922355652)",
      "stroke_opacity": 1.0,
      "fill_opacity": null
    },
    {
      "type": "fs",
      "x": 147.8,
      "y": 242.5,
      "w": 15.5,
      "h": 11.6,
      "fill": "(0.7839170098304749, 0.7840390801429749, 0.7839017510414124)",
      "color": "(1.0, 1.0, 1.0)",
      "stroke_opacity": 1.0,
      "fill_opacity": 1.0
    },
    {
      "type": "fs",
      "x": 147.8,
      "y": 261.0,
      "w": 15.5,
      "h": 11.6,
      "fill": "(0.0, 0.7609999775886536, 0.3330000042915344)",
      "color": "(1.0, 1.0, 1.0)",
      "stroke_opacity": 1.0,
      "fill_opacity": 1.0
    },
    {
      "type": "f",
      "x": 702.7,
      "y": 357.2,
      "w": 20.0,
      "h": 20.0,
      "fill": "(0.16099999845027924, 0.7289999723434448, 0.45500001311302185)",
      "color": null,
      "stroke_opacity": null,
      "fill_opacity": 1.0
    },
    {
      "type": "f",
      "x": 708.0,
      "y": 363.6,
      "w": 9.4,
      "h": 7.3,
      "fill": "(1.0, 1.0, 1.0)",
      "color": null,
      "stroke_opacity": null,
      "fill_opacity": 1.0
    },
    {
      "type": "f",
      "x": 703.8,
      "y": 416.7,
      "w": 20.0,
      "h": 20.0,
      "fill": "(0.16099999845027924, 0.7289999723434448, 0.45500001311302185)",
      "color": null,
      "stroke_opacity": null,
      "fill_opacity": 1.0
    },
    {
      "type": "f",
      "x": 709.1,
      "y": 423.1,
      "w": 9.4,
      "h": 7.3,
      "fill": "(1.0, 1.0, 1.0)",
      "color": null,
      "stroke_opacity": null,
      "fill_opacity": 1.0
    },
    {
      "type": "s",
      "x": 844.7,
      "y": 18.1,
      "w": 0.0,
      "h": 57.3,
      "fill": null,
      "color": "(1.0, 1.0, 1.0)",
      "stroke_opacity": 1.0,
      "fill_opacity": null
    }
  ],
  "images": [
    {
      "xref": 278,
      "x": 558.7,
      "y": 0.0,
      "w": 401.3,
      "h": 89.2
    }
  ]
}